convertible.py
convertible-0.1.0.dist-info/LICENSE
convertible-0.1.0.dist-info/WHEEL
convertible-0.1.0.dist-info/METADATA
convertible-0.1.0.dist-info/RECORD
