Metadata-Version: 2.1
Name: convertible
Version: 0.1.0
Summary: Value-to-value conversion in Python
Author: Anexen
Requires-Python: >=3.7
Classifier: License :: OSI Approved :: MIT License
Classifier: Intended Audience :: Developers
Classifier: Programming Language :: Python :: 3
Project-URL: Source, https://github.com/Anexen/convertible
